syntropycli/__init__.py
syntropycli/__main__.py
syntropycli/decorators.py
syntropycli/utils.py
syntropycli-0.3.0.dist-info/LICENSE
syntropycli-0.3.0.dist-info/METADATA
syntropycli-0.3.0.dist-info/WHEEL
syntropycli-0.3.0.dist-info/entry_points.txt
syntropycli-0.3.0.dist-info/top_level.txt
syntropycli-0.3.0.dist-info/RECORD
