Metadata-Version: 2.1
Name: syntropycli
Version: 0.3.0
Summary: Syntropy Universal Command Line Interface
Home-page: https://github.com/SyntropyNet/syntropy-cli/
Author: Andrius Mikonis
Author-email: andrius@noia.network
License: MIT
Platform: any
Classifier: Development Status :: 5 - Production/Stable
Classifier: Intended Audience :: Developers
Classifier: Natural Language :: English
Classifier: License :: OSI Approved :: MIT License
Classifier: Programming Language :: Python
Classifier: Programming Language :: Python :: 3.6
Classifier: Programming Language :: Python :: 3.7
Classifier: Programming Language :: Python :: 3.8
Requires-Python: >=3.6
License-File: LICENSE
Requires-Dist: syntropy-sdk
Requires-Dist: click (<=8.0.4)
Requires-Dist: prettytable (<=2.5.0)
